README.rst
setup.cfg
setup.py
chtool/__init__.py
chtool/tool.py
chtool.egg-info/PKG-INFO
chtool.egg-info/SOURCES.txt
chtool.egg-info/dependency_links.txt
chtool.egg-info/requires.txt
chtool.egg-info/top_level.txt
chtool/common/__init__.py
chtool/common/concurrency.py
chtool/common/decorator.py
chtool/dbtool/__init__.py
chtool/dbtool/postgresql.py
chtool/dbtool/lmf/__init__.py
chtool/dbtool/lmf/bigdata.py
chtool/dbtool/lmf/db4.py
chtool/dbtool/lmf/dbv2.py
chtool/dbtool/lmf/publishtool.py
chtool/dbtool/lmf/tool.py
chtool/dbtool/lmf/gp/__init__.py
chtool/dbtool/lmf/gp/api.py
chtool/dbtool/lmf/gp/v1/__init__.py
chtool/dbtool/lmf/gp/v1/etl_pxf.py
chtool/install/__init__.py
chtool/install/airflow/__init__.py
chtool/install/airflow/airflow_cluster.py
chtool/install/airflow/airflow_single.py
chtool/install/common/__init__.py
chtool/install/common/base.py
chtool/install/common/dns.py
chtool/install/common/firewalld.py
chtool/install/common/hostname.py
chtool/install/common/java.py
chtool/install/common/mount.py
chtool/install/common/ssh.py
chtool/install/common/swap.py
chtool/install/common/yum.py
chtool/install/elk/__init__.py
chtool/install/elk/elasticsearch.py
chtool/install/elk/elk.py
chtool/install/elk/kibana.py
chtool/install/elk/logstach.py
chtool/install/greenplum/__init__.py
chtool/install/hadoop/__init__.py
chtool/install/hadoop/cdh/__init__.py
chtool/install/kafka/__init__.py
chtool/install/kafka/kafka_.py
chtool/install/kafka/kafka_consumer.py
chtool/install/kafka/kafka_consumer_group.py
chtool/install/kafka/kafka_producer.py
chtool/install/lmfinstall/__init__.py
chtool/install/lmfinstall/common.py
chtool/install/lmfinstall/publishtool.py
chtool/install/lmfinstall/task.py
chtool/install/lmfinstall/airflow/__init__.py
chtool/install/lmfinstall/airflow/airflow103.py
chtool/install/lmfinstall/ambari/__init__.py
chtool/install/lmfinstall/ambari/core.py
chtool/install/lmfinstall/ambari/v1/__init__.py
chtool/install/lmfinstall/ambari/v1/core.py
chtool/install/lmfinstall/cdh/__init__.py
chtool/install/lmfinstall/cdh/core.py
chtool/install/lmfinstall/exam/__init__.py
chtool/install/lmfinstall/exam/bdsdk.py
